.readthedocs.yml
CONTRIBUTING.md
LICENSE
MANIFEST.in
Makefile
README.md
pyproject.toml
pytest.ini
requirements.txt
setup.py
docs/Makefile
docs/api.rst
docs/conf.py
docs/contributing.rst
docs/fit_tutorial.rst
docs/get_started.rst
docs/index.rst
docs/license.rst
docs/make.bat
docs/mcmc_tutorial.rst
docs/references.rst
docs/time_averaging.rst
docs/figures/quad_bestfit.png
docs/figures/quad_fitting.png
docs/figures/quad_hist.png
docs/figures/quad_pairwise.png
docs/figures/quad_trace.png
docs/figures/rms-vs-binsize.png
examples/get_started.py
examples/timeavg.py
examples/tutorial.py
mc3/__init__.py
mc3/__main__.py
mc3/chain.py
mc3/fit_driver.py
mc3/mcmc_driver.py
mc3/sampler_driver.py
mc3/version.py
mc3.egg-info/PKG-INFO
mc3.egg-info/SOURCES.txt
mc3.egg-info/dependency_links.txt
mc3.egg-info/entry_points.txt
mc3.egg-info/requires.txt
mc3.egg-info/top_level.txt
mc3/plots/__init__.py
mc3/plots/colors.py
mc3/plots/plot_functions.py
mc3/plots/posterior.py
mc3/stats/__init__.py
mc3/stats/gelman.py
mc3/stats/prayer.py
mc3/stats/stats.py
mc3/stats/time_averaging.py
mc3/utils/__init__.py
mc3/utils/log.py
mc3/utils/utils.py
src_c/_binarray.c
src_c/_chisq.c
src_c/_dwt.c
src_c/_time_averaging.c
src_c/include/ind.h
src_c/include/stats.h
src_c/include/wavelet.h
tests/test_fit.py
tests/test_logging.py
tests/test_mcmc.py
tests/test_plots.py
tests/test_stats.py
tests/test_utils.py