Metadata-Version: 2.2
Name: mc3
Version: 3.2.1
Summary: Multi-core Markov-chain Monte Carlo package
Author-email: Patricio Cubillos <patricio.cubillos@oeaw.ac.at>
License: Copyright (c) 2015-2022 Patricio Cubillos and contributors.
Project-URL: Homepage, https://github.com/pcubillos/mc3
Requires-Python: >=3.9
License-File: LICENSE
Requires-Dist: numpy>=1.23.5
Requires-Dist: scipy>=1.5.4
Requires-Dist: matplotlib>=3.3.4
Provides-Extra: test
Requires-Dist: pytest>=6.0; extra == "test"
